<?xml version="1.0" encoding="UTF-8"?>
<widget X="-391" Y="845">
  <list>
    <list>
      <item>
        <name>Battery</name>
        <type>1</type>
        <size>54</size>
        <image>.\Images\info.png</image>
      </item>
      <item>
        <name>Raekh</name>
        <type>3</type>
        <size>236</size>
        <data>
          <source>00000001-4F00-6144-7461-536F75726365</source>
          <data>BA8D07C2-FA60-4BBB-84C4-5644FEA35388</data>
          <value>2</value>
          <mode>0</mode>
          <interval>1000</interval>
          <unit>%</unit>
        </data>
      </item>
    </list>
    <list>
      <item>
        <name>RAM</name>
        <type>1</type>
        <size>54</size>
        <image>.\Images\weapon.png</image>
      </item>
      <item>
        <name>RAM</name>
        <type>2</type>
        <size>54</size>
        <data>
          <source>00000001-4f00-6144-7461-536f75726365</source>
          <data>766a81e5-fc74-4c10-9020-27280857b1cb</data>
          <value>0</value>
          <mode>0</mode>
          <interval>1000</interval>
          <unit>%</unit>
        </data>
      </item>
      <item>
        <name>RAM</name>
        <type>4</type>
        <size>182</size>
        <data>
          <source>00000001-4f00-6144-7461-536f75726365</source>
          <data>766a81e5-fc74-4c10-9020-27280857b1cb</data>
          <value>0</value>
          <mode>0</mode>
          <interval>1000</interval>
          <unit>MB</unit>
        </data>
      </item>
    </list>
    <list>
      <item>
        <name>HDD</name>
        <type>1</type>
        <size>54</size>
        <image>.\Images\weapon.png</image>
      </item>
      <item>
        <name>HDD</name>
        <type>2</type>
        <size>54</size>
        <data>
          <source>00000001-4f00-6144-7461-536f75726365</source>
          <data>529dd40a-12a4-4196-af7a-9a174943134b</data>
          <value>0</value>
          <mode>0</mode>
          <interval>60000</interval>
          <unit>%</unit>
        </data>
      </item>
      <item>
        <name>HDD</name>
        <type>4</type>
        <size>114</size>
        <data>
          <source>00000001-4f00-6144-7461-536f75726365</source>
          <data>529dd40a-12a4-4196-af7a-9a174943134b</data>
          <value>0</value>
          <mode>0</mode>
          <interval>10000</interval>
          <unit>MB</unit>
        </data>
      </item>
    </list>
  </list>
</widget>
